cql2-0.4.2.dist-info/METADATA
cql2-0.4.2.dist-info/WHEEL
cql2-0.4.2.dist-info/entry_points.txt
cql2-0.4.2.dist-info/licenses/LICENSE
cql2/__init__.py
cql2/__init__.pyi
cql2/cql2.abi3.so
cql2/py.typed
cql2-0.4.2.dist-info/RECORD
