Metadata-Version: 2.4
Name: cql2
Version: 0.4.2
Classifier: Programming Language :: Rust
Classifier: Programming Language :: Python :: Implementation :: CPython
Classifier: Programming Language :: Python :: Implementation :: PyPy
Classifier: Programming Language :: Python :: 3.10
Classifier: Programming Language :: Python :: 3.11
Classifier: Programming Language :: Python :: 3.12
Classifier: Programming Language :: Python :: 3.13
Classifier: Programming Language :: Python :: 3.14
License-File: LICENSE
Summary: Parse, validate, and convert Common Query Language (CQL2) text and JSON
Keywords: cql2
Home-Page: https://github.com/developmentseed/cql2-rs
License: MIT
Requires-Python: >=3.10
